.dockerignore
.editorconfig
AUTHORS.rst
CHANGES.rst
LICENSE
MANIFEST.in
README.rst
setup.cfg
setup.py
.tx/config
invenio_dnb_urn/__init__.py
invenio_dnb_urn/config.py
invenio_dnb_urn/errors.py
invenio_dnb_urn/oai.py
invenio_dnb_urn/utils.py
invenio_dnb_urn/views.py
invenio_dnb_urn.egg-info/PKG-INFO
invenio_dnb_urn.egg-info/SOURCES.txt
invenio_dnb_urn.egg-info/dependency_links.txt
invenio_dnb_urn.egg-info/entry_points.txt
invenio_dnb_urn.egg-info/not-zip-safe
invenio_dnb_urn.egg-info/requires.txt
invenio_dnb_urn.egg-info/top_level.txt
invenio_dnb_urn/provider/__init__.py
invenio_dnb_urn/provider/dnburn.py
invenio_dnb_urn/serialize/__init__.py
invenio_dnb_urn/serialize/xmetadiss.py
tests/test_invenio_dnb_urn.py